book_cover_maker/__init__.py
book_cover_maker/gen_cover.py
book_cover_maker-0.1.17.data/data/cover_background.jpg
book_cover_maker-0.1.17.data/data/fonts/NotoColorEmoji-Regular.ttf
book_cover_maker-0.1.17.data/data/fonts/NotoKufiArabic-Bold.ttf
book_cover_maker-0.1.17.data/data/fonts/NotoKufiArabic-Regular.ttf
book_cover_maker-0.1.17.data/data/fonts/NotoNaskhArabic-Bold.ttf
book_cover_maker-0.1.17.data/data/fonts/NotoNaskhArabic-Regular.ttf
book_cover_maker-0.1.17.data/data/fonts/NotoSans-Bold.ttf
book_cover_maker-0.1.17.data/data/fonts/NotoSans-BoldItalic.ttf
book_cover_maker-0.1.17.data/data/fonts/NotoSans-Italic.ttf
book_cover_maker-0.1.17.data/data/fonts/NotoSans-Regular.ttf
book_cover_maker-0.1.17.data/data/fonts/NotoSansArabic-Bold.ttf
book_cover_maker-0.1.17.data/data/fonts/NotoSansArabic-Regular.ttf
book_cover_maker-0.1.17.data/data/fonts/NotoSansArmenian-Bold.ttf
book_cover_maker-0.1.17.data/data/fonts/NotoSansArmenian-Regular.ttf
book_cover_maker-0.1.17.data/data/fonts/NotoSansGeorgian-Bold.ttf
book_cover_maker-0.1.17.data/data/fonts/NotoSansGeorgian-Regular.ttf
book_cover_maker-0.1.17.data/data/fonts/NotoSansHK-VF.ttf
book_cover_maker-0.1.17.data/data/fonts/NotoSansHebrew-Bold.ttf
book_cover_maker-0.1.17.data/data/fonts/NotoSansHebrew-Regular.ttf
book_cover_maker-0.1.17.data/data/fonts/NotoSansJP-VF.ttf
book_cover_maker-0.1.17.data/data/fonts/NotoSansKR-Black.ttf
book_cover_maker-0.1.17.data/data/fonts/NotoSansKR-Bold.ttf
book_cover_maker-0.1.17.data/data/fonts/NotoSansKR-ExtraBold.ttf
book_cover_maker-0.1.17.data/data/fonts/NotoSansKR-ExtraLight.ttf
book_cover_maker-0.1.17.data/data/fonts/NotoSansKR-Light.ttf
book_cover_maker-0.1.17.data/data/fonts/NotoSansKR-Medium.ttf
book_cover_maker-0.1.17.data/data/fonts/NotoSansKR-Regular.ttf
book_cover_maker-0.1.17.data/data/fonts/NotoSansKR-SemiBold.ttf
book_cover_maker-0.1.17.data/data/fonts/NotoSansKR-Thin.ttf
book_cover_maker-0.1.17.data/data/fonts/NotoSansKR-VF.ttf
book_cover_maker-0.1.17.dist-info/METADATA
book_cover_maker-0.1.17.dist-info/WHEEL
book_cover_maker-0.1.17.dist-info/entry_points.txt
book_cover_maker-0.1.17.dist-info/RECORD
