Metadata-Version: 2.3
Name: book-cover-maker
Version: 0.1.17
Summary: A tool to generate book covers with customizable text and fonts
Project-URL: Homepage, https://github.com/hakunamta00700/book_cover_maker
Project-URL: Repository, https://github.com/hakunamta00700/book_cover_maker
Project-URL: Issues, https://github.com/hakunamta00700/book_cover_maker/issues
Author-email: David Cho <csi00700@gmail.com>
Requires-Python: >=3.9
Requires-Dist: pillow>=11.3.0
Requires-Dist: typer>=0.12.0
Requires-Dist: uv-easy>=0.2.53
